django_ussd
