Metadata-Version: 1.0
Name: simulator-ussd
Version: 0.0.2
Summary: USSD util for Django
Home-page: https://bitbucket.org/wezatele/django-ussd
Author: Elias
Author-email: elias.kioni@gmail.com
License: MIT License
Platform: UNKNOWN
